[
  {
    "date": "2025-10-26",
    "stock": 1.8,
    "vnindex": 1.08
  },
  {
    "date": "2025-10-27",
    "stock": 3.92,
    "vnindex": 2.7
  },
  {
    "date": "2025-10-28",
    "stock": 3.76,
    "vnindex": 2.47
  },
  {
    "date": "2025-10-29",
    "stock": 2.71,
    "vnindex": 1.18
  },
  {
    "date": "2025-10-30",
    "stock": 2.12,
    "vnindex": 0.33
  },
  {
    "date": "2025-10-31",
    "stock": 1.18,
    "vnindex": -0.12
  },
  {
    "date": "2025-11-01",
    "stock": 0.67,
    "vnindex": -0.29
  },
  {
    "date": "2025-11-02",
    "stock": 1.19,
    "vnindex": 0.89
  },
  {
    "date": "2025-11-03",
    "stock": 1.3,
    "vnindex": 1.5
  },
  {
    "date": "2025-11-04",
    "stock": 3.15,
    "vnindex": 2.96
  },
  {
    "date": "2025-11-05",
    "stock": 4.34,
    "vnindex": 3.18
  },
  {
    "date": "2025-11-06",
    "stock": 4.23,
    "vnindex": 3.56
  },
  {
    "date": "2025-11-07",
    "stock": 4.44,
    "vnindex": 3.64
  },
  {
    "date": "2025-11-08",
    "stock": 5.08,
    "vnindex": 4.19
  },
  {
    "date": "2025-11-09",
    "stock": 4.56,
    "vnindex": 3.82
  },
  {
    "date": "2025-11-10",
    "stock": 3.37,
    "vnindex": 2.74
  },
  {
    "date": "2025-11-11",
    "stock": 3.9,
    "vnindex": 3.45
  },
  {
    "date": "2025-11-12",
    "stock": 4.08,
    "vnindex": 4.34
  },
  {
    "date": "2025-11-13",
    "stock": 2.47,
    "vnindex": 3.13
  },
  {
    "date": "2025-11-14",
    "stock": 2.78,
    "vnindex": 3.28
  },
  {
    "date": "2025-11-15",
    "stock": 3.19,
    "vnindex": 3.67
  },
  {
    "date": "2025-11-16",
    "stock": 4.25,
    "vnindex": 4.6
  },
  {
    "date": "2025-11-17",
    "stock": 5.93,
    "vnindex": 5.32
  },
  {
    "date": "2025-11-18",
    "stock": 6.65,
    "vnindex": 6.19
  },
  {
    "date": "2025-11-19",
    "stock": 6.61,
    "vnindex": 6.31
  },
  {
    "date": "2025-11-20",
    "stock": 8.08,
    "vnindex": 7.22
  },
  {
    "date": "2025-11-21",
    "stock": 8.07,
    "vnindex": 7.64
  },
  {
    "date": "2025-11-22",
    "stock": 9.33,
    "vnindex": 7.99
  },
  {
    "date": "2025-11-23",
    "stock": 8.63,
    "vnindex": 7.72
  },
  {
    "date": "2025-11-24",
    "stock": 8.76,
    "vnindex": 8.06
  },
  {
    "date": "2025-11-25",
    "stock": 8.86,
    "vnindex": 7.78
  },
  {
    "date": "2025-11-26",
    "stock": 8.2,
    "vnindex": 6.75
  },
  {
    "date": "2025-11-27",
    "stock": 7.55,
    "vnindex": 5.72
  },
  {
    "date": "2025-11-28",
    "stock": 6.96,
    "vnindex": 5.39
  },
  {
    "date": "2025-11-29",
    "stock": 6.59,
    "vnindex": 4.85
  },
  {
    "date": "2025-11-30",
    "stock": 4.64,
    "vnindex": 3.28
  },
  {
    "date": "2025-12-01",
    "stock": 3.6,
    "vnindex": 2.56
  },
  {
    "date": "2025-12-02",
    "stock": 3.3,
    "vnindex": 2.72
  },
  {
    "date": "2025-12-03",
    "stock": 3.63,
    "vnindex": 3.61
  },
  {
    "date": "2025-12-04",
    "stock": 3.03,
    "vnindex": 3.42
  },
  {
    "date": "2025-12-05",
    "stock": 3.32,
    "vnindex": 3.26
  },
  {
    "date": "2025-12-06",
    "stock": 3.14,
    "vnindex": 3.19
  },
  {
    "date": "2025-12-07",
    "stock": 4.33,
    "vnindex": 3.73
  },
  {
    "date": "2025-12-08",
    "stock": 4.32,
    "vnindex": 3.67
  },
  {
    "date": "2025-12-09",
    "stock": 5.05,
    "vnindex": 4.73
  },
  {
    "date": "2025-12-10",
    "stock": 6.14,
    "vnindex": 4.97
  },
  {
    "date": "2025-12-11",
    "stock": 5.13,
    "vnindex": 4.03
  },
  {
    "date": "2025-12-12",
    "stock": 4.52,
    "vnindex": 3.64
  },
  {
    "date": "2025-12-13",
    "stock": 6.24,
    "vnindex": 5.56
  },
  {
    "date": "2025-12-14",
    "stock": 6.08,
    "vnindex": 5.5
  },
  {
    "date": "2025-12-15",
    "stock": 6.68,
    "vnindex": 5.75
  },
  {
    "date": "2025-12-16",
    "stock": 5.61,
    "vnindex": 5.3
  },
  {
    "date": "2025-12-17",
    "stock": 4.9,
    "vnindex": 4.62
  },
  {
    "date": "2025-12-18",
    "stock": 4.46,
    "vnindex": 4.81
  },
  {
    "date": "2025-12-19",
    "stock": 4.01,
    "vnindex": 3.18
  },
  {
    "date": "2025-12-20",
    "stock": 4.99,
    "vnindex": 3.67
  },
  {
    "date": "2025-12-21",
    "stock": 5.66,
    "vnindex": 4.14
  },
  {
    "date": "2025-12-22",
    "stock": 5.46,
    "vnindex": 4.51
  },
  {
    "date": "2025-12-23",
    "stock": 7.23,
    "vnindex": 5.58
  },
  {
    "date": "2025-12-24",
    "stock": 6.3,
    "vnindex": 5.29
  },
  {
    "date": "2025-12-25",
    "stock": 7.2,
    "vnindex": 5.63
  },
  {
    "date": "2025-12-26",
    "stock": 7.18,
    "vnindex": 6.33
  },
  {
    "date": "2025-12-27",
    "stock": 5.98,
    "vnindex": 4.74
  },
  {
    "date": "2025-12-28",
    "stock": 5.5,
    "vnindex": 3.6
  },
  {
    "date": "2025-12-29",
    "stock": 5.49,
    "vnindex": 3.09
  },
  {
    "date": "2025-12-30",
    "stock": 5.16,
    "vnindex": 2.5
  },
  {
    "date": "2025-12-31",
    "stock": 6.37,
    "vnindex": 3.13
  },
  {
    "date": "2026-01-01",
    "stock": 7.6,
    "vnindex": 4.48
  },
  {
    "date": "2026-01-02",
    "stock": 7.84,
    "vnindex": 5.11
  },
  {
    "date": "2026-01-03",
    "stock": 8.28,
    "vnindex": 5.22
  },
  {
    "date": "2026-01-04",
    "stock": 7.92,
    "vnindex": 5.58
  },
  {
    "date": "2026-01-05",
    "stock": 8.43,
    "vnindex": 6.11
  },
  {
    "date": "2026-01-06",
    "stock": 6.87,
    "vnindex": 5.15
  },
  {
    "date": "2026-01-07",
    "stock": 6.35,
    "vnindex": 4.86
  },
  {
    "date": "2026-01-08",
    "stock": 7.71,
    "vnindex": 5.74
  },
  {
    "date": "2026-01-09",
    "stock": 9.11,
    "vnindex": 6.41
  },
  {
    "date": "2026-01-10",
    "stock": 9.09,
    "vnindex": 5.6
  },
  {
    "date": "2026-01-11",
    "stock": 9.59,
    "vnindex": 5.98
  },
  {
    "date": "2026-01-12",
    "stock": 10.97,
    "vnindex": 6.99
  },
  {
    "date": "2026-01-13",
    "stock": 9.77,
    "vnindex": 5.7
  },
  {
    "date": "2026-01-14",
    "stock": 9.96,
    "vnindex": 5.47
  },
  {
    "date": "2026-01-15",
    "stock": 10.6,
    "vnindex": 5.82
  },
  {
    "date": "2026-01-16",
    "stock": 9.08,
    "vnindex": 5.48
  },
  {
    "date": "2026-01-17",
    "stock": 9.61,
    "vnindex": 6.78
  },
  {
    "date": "2026-01-18",
    "stock": 8.63,
    "vnindex": 5.77
  },
  {
    "date": "2026-01-19",
    "stock": 8.86,
    "vnindex": 5.46
  },
  {
    "date": "2026-01-20",
    "stock": 8.27,
    "vnindex": 4.99
  },
  {
    "date": "2026-01-21",
    "stock": 8.35,
    "vnindex": 4.87
  },
  {
    "date": "2026-01-22",
    "stock": 8.56,
    "vnindex": 4.6
  },
  {
    "date": "2026-01-23",
    "stock": 8.14,
    "vnindex": 4.26
  },
  {
    "date": "2026-01-24",
    "stock": 7.96,
    "vnindex": 3.58
  },
  {
    "date": "2026-01-25",
    "stock": 6.72,
    "vnindex": 2.39
  },
  {
    "date": "2026-01-26",
    "stock": 5.26,
    "vnindex": 1.23
  },
  {
    "date": "2026-01-27",
    "stock": 6.07,
    "vnindex": 0.36
  },
  {
    "date": "2026-01-28",
    "stock": 5.85,
    "vnindex": -0.45
  },
  {
    "date": "2026-01-29",
    "stock": 6.16,
    "vnindex": 0.08
  },
  {
    "date": "2026-01-30",
    "stock": 6.77,
    "vnindex": 1.19
  },
  {
    "date": "2026-01-31",
    "stock": 6.34,
    "vnindex": 1.39
  },
  {
    "date": "2026-02-01",
    "stock": 5.07,
    "vnindex": -0.02
  },
  {
    "date": "2026-02-02",
    "stock": 5.82,
    "vnindex": 0.51
  },
  {
    "date": "2026-02-03",
    "stock": 6.33,
    "vnindex": 0.95
  },
  {
    "date": "2026-02-04",
    "stock": 6.36,
    "vnindex": 0.65
  },
  {
    "date": "2026-02-05",
    "stock": 7.28,
    "vnindex": 1.15
  },
  {
    "date": "2026-02-06",
    "stock": 6.34,
    "vnindex": 0.65
  },
  {
    "date": "2026-02-07",
    "stock": 5.34,
    "vnindex": -0.19
  },
  {
    "date": "2026-02-08",
    "stock": 3.4,
    "vnindex": -1.17
  },
  {
    "date": "2026-02-09",
    "stock": 3.48,
    "vnindex": -1.1
  },
  {
    "date": "2026-02-10",
    "stock": 4.63,
    "vnindex": 0.28
  },
  {
    "date": "2026-02-11",
    "stock": 4.15,
    "vnindex": 0.05
  },
  {
    "date": "2026-02-12",
    "stock": 4.36,
    "vnindex": 0.28
  },
  {
    "date": "2026-02-13",
    "stock": 5.48,
    "vnindex": 0.4
  },
  {
    "date": "2026-02-14",
    "stock": 8.32,
    "vnindex": 3.18
  },
  {
    "date": "2026-02-15",
    "stock": 8.21,
    "vnindex": 3.15
  },
  {
    "date": "2026-02-16",
    "stock": 8.56,
    "vnindex": 3.57
  },
  {
    "date": "2026-02-17",
    "stock": 6.82,
    "vnindex": 2.06
  },
  {
    "date": "2026-02-18",
    "stock": 7.57,
    "vnindex": 2.85
  },
  {
    "date": "2026-02-19",
    "stock": 7.2,
    "vnindex": 2.28
  },
  {
    "date": "2026-02-20",
    "stock": 7.3,
    "vnindex": 1.7
  },
  {
    "date": "2026-02-21",
    "stock": 8.13,
    "vnindex": 2.72
  },
  {
    "date": "2026-02-22",
    "stock": 9.19,
    "vnindex": 2.71
  },
  {
    "date": "2026-02-23",
    "stock": 10.64,
    "vnindex": 4.04
  },
  {
    "date": "2026-02-24",
    "stock": 11.93,
    "vnindex": 4.06
  },
  {
    "date": "2026-02-25",
    "stock": 10.95,
    "vnindex": 3.68
  },
  {
    "date": "2026-02-26",
    "stock": 10.33,
    "vnindex": 3.6
  },
  {
    "date": "2026-02-27",
    "stock": 11.23,
    "vnindex": 3.49
  },
  {
    "date": "2026-02-28",
    "stock": 11.15,
    "vnindex": 4.39
  },
  {
    "date": "2026-03-01",
    "stock": 12.33,
    "vnindex": 4.49
  },
  {
    "date": "2026-03-02",
    "stock": 12.23,
    "vnindex": 4.84
  },
  {
    "date": "2026-03-03",
    "stock": 11.04,
    "vnindex": 4.05
  },
  {
    "date": "2026-03-04",
    "stock": 11.75,
    "vnindex": 5.1
  },
  {
    "date": "2026-03-05",
    "stock": 10.54,
    "vnindex": 4.39
  },
  {
    "date": "2026-03-06",
    "stock": 9.87,
    "vnindex": 4.32
  },
  {
    "date": "2026-03-07",
    "stock": 10.12,
    "vnindex": 4.35
  },
  {
    "date": "2026-03-08",
    "stock": 8.7,
    "vnindex": 3.53
  },
  {
    "date": "2026-03-09",
    "stock": 10.0,
    "vnindex": 4.77
  },
  {
    "date": "2026-03-10",
    "stock": 8.74,
    "vnindex": 3.67
  },
  {
    "date": "2026-03-11",
    "stock": 10.53,
    "vnindex": 5.06
  },
  {
    "date": "2026-03-12",
    "stock": 11.02,
    "vnindex": 5.88
  },
  {
    "date": "2026-03-13",
    "stock": 11.38,
    "vnindex": 5.56
  },
  {
    "date": "2026-03-14",
    "stock": 12.46,
    "vnindex": 6.55
  },
  {
    "date": "2026-03-15",
    "stock": 10.66,
    "vnindex": 5.75
  },
  {
    "date": "2026-03-16",
    "stock": 10.32,
    "vnindex": 5.86
  },
  {
    "date": "2026-03-17",
    "stock": 10.68,
    "vnindex": 6.47
  },
  {
    "date": "2026-03-18",
    "stock": 11.57,
    "vnindex": 6.66
  },
  {
    "date": "2026-03-19",
    "stock": 14.16,
    "vnindex": 8.71
  },
  {
    "date": "2026-03-20",
    "stock": 14.11,
    "vnindex": 8.82
  },
  {
    "date": "2026-03-21",
    "stock": 14.1,
    "vnindex": 8.72
  },
  {
    "date": "2026-03-22",
    "stock": 12.46,
    "vnindex": 7.39
  },
  {
    "date": "2026-03-23",
    "stock": 10.33,
    "vnindex": 5.85
  },
  {
    "date": "2026-03-24",
    "stock": 11.91,
    "vnindex": 7.06
  },
  {
    "date": "2026-03-25",
    "stock": 10.43,
    "vnindex": 5.75
  },
  {
    "date": "2026-03-26",
    "stock": 10.9,
    "vnindex": 5.82
  },
  {
    "date": "2026-03-27",
    "stock": 9.99,
    "vnindex": 5.39
  },
  {
    "date": "2026-03-28",
    "stock": 9.26,
    "vnindex": 4.47
  },
  {
    "date": "2026-03-29",
    "stock": 10.02,
    "vnindex": 5.28
  },
  {
    "date": "2026-03-30",
    "stock": 9.55,
    "vnindex": 3.91
  },
  {
    "date": "2026-03-31",
    "stock": 10.05,
    "vnindex": 3.9
  },
  {
    "date": "2026-04-01",
    "stock": 10.75,
    "vnindex": 4.8
  },
  {
    "date": "2026-04-02",
    "stock": 10.68,
    "vnindex": 4.15
  },
  {
    "date": "2026-04-03",
    "stock": 9.57,
    "vnindex": 3.24
  },
  {
    "date": "2026-04-04",
    "stock": 10.18,
    "vnindex": 3.66
  },
  {
    "date": "2026-04-05",
    "stock": 10.46,
    "vnindex": 3.83
  },
  {
    "date": "2026-04-06",
    "stock": 11.34,
    "vnindex": 4.53
  },
  {
    "date": "2026-04-07",
    "stock": 11.76,
    "vnindex": 4.53
  },
  {
    "date": "2026-04-08",
    "stock": 12.48,
    "vnindex": 4.6
  },
  {
    "date": "2026-04-09",
    "stock": 12.24,
    "vnindex": 4.2
  },
  {
    "date": "2026-04-10",
    "stock": 12.61,
    "vnindex": 4.92
  },
  {
    "date": "2026-04-11",
    "stock": 12.07,
    "vnindex": 5.01
  },
  {
    "date": "2026-04-12",
    "stock": 11.28,
    "vnindex": 4.44
  },
  {
    "date": "2026-04-13",
    "stock": 11.8,
    "vnindex": 4.45
  },
  {
    "date": "2026-04-14",
    "stock": 10.67,
    "vnindex": 3.78
  },
  {
    "date": "2026-04-15",
    "stock": 10.56,
    "vnindex": 3.79
  },
  {
    "date": "2026-04-16",
    "stock": 10.57,
    "vnindex": 4.24
  },
  {
    "date": "2026-04-17",
    "stock": 10.68,
    "vnindex": 4.51
  },
  {
    "date": "2026-04-18",
    "stock": 9.64,
    "vnindex": 3.49
  },
  {
    "date": "2026-04-19",
    "stock": 8.41,
    "vnindex": 1.88
  },
  {
    "date": "2026-04-20",
    "stock": 6.94,
    "vnindex": 0.81
  },
  {
    "date": "2026-04-21",
    "stock": 6.92,
    "vnindex": 0.85
  },
  {
    "date": "2026-04-22",
    "stock": 7.85,
    "vnindex": 0.88
  },
  {
    "date": "2026-04-23",
    "stock": 6.16,
    "vnindex": -0.17
  }
]